{
  "db_name": "PostgreSQL",
  "query": "\n      update store_invites\n      set revoked_at = now(), modified_at = now()\n      where id = $1\n      returning \n        id, \n        store_id, \n        email, \n        accepted_at, \n        revoked_at, \n        created_at, \n        modified_at\n    ",
  "describe": {
    "columns": [
      {
        "ordinal": 0,
        "name": "id",
        "type_info": "Uuid"
      },
      {
        "ordinal": 1,
        "name": "store_id",
        "type_info": "Uuid"
      },
      {
        "ordinal": 2,
        "name": "email",
        "type_info": "Text"
      },
      {
        "ordinal": 3,
        "name": "accepted_at",
        "type_info": "Timestamptz"
      },
      {
        "ordinal": 4,
        "name": "revoked_at",
        "type_info": "Timestamptz"
      },
      {
        "ordinal": 5,
        "name": "created_at",
        "type_info": "Timestamptz"
      },
      {
        "ordinal": 6,
        "name": "modified_at",
        "type_info": "Timestamptz"
      }
    ],
    "parameters": {
      "Left": [
        "Uuid"
      ]
    },
    "nullable": [
      false,
      false,
      false,
      true,
      true,
      false,
      true
    ]
  },
  "hash": "89022c0921259349352043e528aaf1a72f8e6d96ad22db1a9dd7610fb6e4723e"
}
